[1,["c2dm6gym1JRakCyqLmdAWi"],0,[["sp.SkeletonData",["_name","_atlasText","textureNames","_skeletonJson","textures"],-1,3]],[[0,0,1,2,3,4,5]],[[0,"VFX_TotalWin_Frame","\nVFX_TotalWin_Frame.png\nsize: 736,109\nformat: RGBA8888\nfilter: Linear,Linear\nrepeat: none\nFrame\n  rotate: false\n  xy: 2, 2\n  size: 407, 105\n  orig: 407, 105\n  offset: 0, 0\n  index: -1\nLight\n  rotate: false\n  xy: 676, 48\n  size: 58, 59\n  orig: 58, 59\n  offset: 0, 0\n  index: -1\nLight_Frame\n  rotate: false\n  xy: 411, 45\n  size: 263, 62\n  orig: 263, 62\n  offset: 0, 0\n  index: -1\nstar\n  rotate: false\n  xy: 411, 32\n  size: 11, 11\n  orig: 11, 11\n  offset: 0, 0\n  index: -1\n",["VFX_TotalWin_Frame.png"],{"skeleton":{"hash":"VGT3m2bixSrJQzb4JkC3BHNgd4c","spine":"3.7.94","width":262.65,"height":62.35,"images":"./Images/","audio":""},"bones":[{"name":"root"},{"name":"SCALE_720","parent":"root","scaleX":0.67,"scaleY":0.67},{"name":"L_All","parent":"SCALE_720"},{"name":"L","parent":"L_All","rotation":-2.13,"x":-189.86,"y":7.35,"scaleX":0.354,"scaleY":0.354},{"name":"L2","parent":"L_All","rotation":-6.07,"x":-167.25,"y":24.25,"scaleX":0.265,"scaleY":0.265},{"name":"L3","parent":"L_All","rotation":11.19,"x":-157.26,"y":-12.41,"scaleX":0.6,"scaleY":0.6},{"name":"L5","parent":"L_All","rotation":4.77,"x":-191.45,"y":30.24,"scaleX":0.144,"scaleY":0.144},{"name":"L6","parent":"L_All","rotation":4.77,"x":-186.01,"y":-15.46,"scaleX":0.112,"scaleY":0.112},{"name":"L_All2","parent":"SCALE_720","scaleX":-1},{"name":"L7","parent":"L_All2","rotation":-2.13,"x":-189.86,"y":7.35,"scaleX":0.354,"scaleY":0.354},{"name":"L8","parent":"L_All2","rotation":-6.07,"x":-167.25,"y":24.25,"scaleX":0.265,"scaleY":0.265},{"name":"L9","parent":"L_All2","rotation":11.19,"x":-157.26,"y":-12.41,"scaleX":0.6,"scaleY":0.6},{"name":"L11","parent":"L_All2","rotation":4.77,"x":-191.45,"y":30.24,"scaleX":0.144,"scaleY":0.144},{"name":"L12","parent":"L_All2","rotation":4.77,"x":-186.01,"y":-15.46,"scaleX":0.112,"scaleY":0.112},{"name":"All_Light_Particle2","parent":"SCALE_720","rotation":-0.05,"scaleX":-1},{"name":"Light22","parent":"All_Light_Particle2"},{"name":"Light24","parent":"All_Light_Particle2"},{"name":"Light26","parent":"All_Light_Particle2"},{"name":"Light27","parent":"All_Light_Particle2"},{"name":"Light28","parent":"All_Light_Particle2"},{"name":"Light30","parent":"All_Light_Particle2"},{"name":"Light31","parent":"All_Light_Particle2"},{"name":"Light33","parent":"All_Light_Particle2"},{"name":"Light34","parent":"All_Light_Particle2"},{"name":"Light35","parent":"All_Light_Particle2"},{"name":"Light36","parent":"All_Light_Particle2"},{"name":"Light38","parent":"All_Light_Particle2"},{"name":"Light39","parent":"All_Light_Particle2"},{"name":"Light40","parent":"All_Light_Particle2"},{"name":"Light41","parent":"All_Light_Particle2"},{"name":"Light42","parent":"All_Light_Particle2"},{"name":"All_Light_Particle3","parent":"SCALE_720","rotation":-0.05},{"name":"Light23","parent":"All_Light_Particle3"},{"name":"Light25","parent":"All_Light_Particle3"},{"name":"Light29","parent":"All_Light_Particle3"},{"name":"Light32","parent":"All_Light_Particle3"},{"name":"Light37","parent":"All_Light_Particle3"},{"name":"Light43","parent":"All_Light_Particle3"},{"name":"Light44","parent":"All_Light_Particle3"},{"name":"Light45","parent":"All_Light_Particle3"},{"name":"Light46","parent":"All_Light_Particle3"},{"name":"Light47","parent":"All_Light_Particle3"},{"name":"Light48","parent":"All_Light_Particle3"},{"name":"Light49","parent":"All_Light_Particle3"},{"name":"Light50","parent":"All_Light_Particle3"},{"name":"Light51","parent":"All_Light_Particle3"},{"name":"Light52","parent":"All_Light_Particle3"},{"name":"Light53","parent":"All_Light_Particle3"}],"slots":[{"name":"Frame","bone":"SCALE_720","attachment":"Frame"},{"name":"Clip_Frame","bone":"SCALE_720","attachment":"Clip_Frame"},{"name":"L","bone":"L","blend":"additive"},{"name":"L7","bone":"L7","blend":"additive"},{"name":"L2","bone":"L2","blend":"additive"},{"name":"L8","bone":"L8","blend":"additive"},{"name":"L3","bone":"L3","blend":"additive"},{"name":"L9","bone":"L9","blend":"additive"},{"name":"L5","bone":"L5","blend":"additive"},{"name":"L11","bone":"L11","blend":"additive"},{"name":"L6","bone":"L6","blend":"additive"},{"name":"L12","bone":"L12","blend":"additive"},{"name":"L_Frame","bone":"SCALE_720","blend":"additive"},{"name":"Light22","bone":"Light22","blend":"additive"},{"name":"Light23","bone":"Light23","blend":"additive"},{"name":"Light25","bone":"Light25","blend":"additive"},{"name":"Light24","bone":"Light24","blend":"additive"},{"name":"Light29","bone":"Light29","blend":"additive"},{"name":"Light32","bone":"Light32","blend":"additive"},{"name":"Light26","bone":"Light26","blend":"additive"},{"name":"Light37","bone":"Light37","blend":"additive"},{"name":"Light43","bone":"Light43","blend":"additive"},{"name":"Light27","bone":"Light27","blend":"additive"},{"name":"Light44","bone":"Light44","blend":"additive"},{"name":"Light45","bone":"Light45","blend":"additive"},{"name":"Light28","bone":"Light28","blend":"additive"},{"name":"Light46","bone":"Light46","blend":"additive"},{"name":"Light47","bone":"Light47","blend":"additive"},{"name":"Light30","bone":"Light30","blend":"additive"},{"name":"Light48","bone":"Light48","blend":"additive"},{"name":"Light49","bone":"Light49","blend":"additive"},{"name":"Light31","bone":"Light31","blend":"additive"},{"name":"Light50","bone":"Light50","blend":"additive"},{"name":"Light51","bone":"Light51","blend":"additive"},{"name":"Light33","bone":"Light33","blend":"additive"},{"name":"Light52","bone":"Light52","blend":"additive"},{"name":"Light53","bone":"Light53","blend":"additive"},{"name":"Light34","bone":"Light34","blend":"additive"},{"name":"Light35","bone":"Light35","blend":"additive"},{"name":"Light36","bone":"Light36","blend":"additive"},{"name":"Light38","bone":"Light38","blend":"additive"},{"name":"Light39","bone":"Light39","blend":"additive"},{"name":"Light40","bone":"Light40","blend":"additive"},{"name":"Light41","bone":"Light41","blend":"additive"},{"name":"Light42","bone":"Light42","blend":"additive"}],"skins":{"default":{"Clip_Frame":{"Clip_Frame":{"type":"clipping","end":"L12","vertexCount":4,"color":"ce3a3aff","vertices":[-196.01,57.87,-196.01,-35.16,195.86,-35.19,196,57.87]}},"Frame":{"Frame":{"width":608,"height":157}},"L":{"Light":{"color":"f7ff00ff","width":87,"height":88}},"L11":{"Light":{"color":"f7ff00ff","width":87,"height":88}},"L12":{"Light":{"color":"f7ff00ff","width":87,"height":88}},"L2":{"Light":{"color":"f7ff00ff","width":87,"height":88}},"L3":{"Light":{"color":"f7ff00ff","width":87,"height":88}},"L5":{"Light":{"color":"f7ff00ff","width":87,"height":88}},"L6":{"Light":{"color":"f7ff00ff","width":87,"height":88}},"L7":{"Light":{"color":"f7ff00ff","width":87,"height":88}},"L8":{"Light":{"color":"f7ff00ff","width":87,"height":88}},"L9":{"Light":{"color":"f7ff00ff","width":87,"height":88}},"L_Frame":{"Light_Frame":{"color":"ff000095","y":11.36,"width":392,"height":93}},"Light22":{"star":{"rotation":0.05,"width":16,"height":16}},"Light23":{"star":{"rotation":0.05,"width":16,"height":16}},"Light24":{"star":{"rotation":0.05,"width":16,"height":16}},"Light25":{"star":{"rotation":0.05,"width":16,"height":16}},"Light26":{"star":{"rotation":0.05,"width":16,"height":16}},"Light27":{"star":{"rotation":0.05,"width":16,"height":16}},"Light28":{"star":{"rotation":0.05,"width":16,"height":16}},"Light29":{"star":{"rotation":0.05,"width":16,"height":16}},"Light30":{"star":{"rotation":0.05,"width":16,"height":16}},"Light31":{"star":{"scaleX":1.5,"scaleY":1.5,"rotation":0.05,"width":16,"height":16}},"Light32":{"star":{"rotation":0.05,"width":16,"height":16}},"Light33":{"star":{"scaleX":1.6,"scaleY":1.6,"rotation":0.05,"width":16,"height":16}},"Light34":{"star":{"scaleX":0.7,"scaleY":0.7,"rotation":0.05,"width":16,"height":16}},"Light35":{"star":{"scaleX":1.8,"scaleY":1.8,"rotation":0.05,"width":16,"height":16}},"Light36":{"star":{"scaleX":1.4,"scaleY":1.4,"rotation":0.05,"width":16,"height":16}},"Light37":{"star":{"rotation":0.05,"width":16,"height":16}},"Light38":{"star":{"scaleX":0.7,"scaleY":0.7,"rotation":0.05,"width":16,"height":16}},"Light39":{"star":{"scaleX":0.5,"scaleY":0.5,"rotation":0.05,"width":16,"height":16}},"Light40":{"star":{"scaleX":1.3,"scaleY":1.3,"rotation":0.05,"width":16,"height":16}},"Light41":{"star":{"scaleX":0.8,"scaleY":0.8,"rotation":0.05,"width":16,"height":16}},"Light42":{"star":{"scaleX":1.5,"scaleY":1.5,"rotation":0.05,"width":16,"height":16}},"Light43":{"star":{"rotation":0.05,"width":16,"height":16}},"Light44":{"star":{"scaleX":1.5,"scaleY":1.5,"rotation":0.05,"width":16,"height":16}},"Light45":{"star":{"scaleX":1.6,"scaleY":1.6,"rotation":0.05,"width":16,"height":16}},"Light46":{"star":{"scaleX":0.7,"scaleY":0.7,"rotation":0.05,"width":16,"height":16}},"Light47":{"star":{"scaleX":1.8,"scaleY":1.8,"rotation":0.05,"width":16,"height":16}},"Light48":{"star":{"scaleX":1.4,"scaleY":1.4,"rotation":0.05,"width":16,"height":16}},"Light49":{"star":{"scaleX":0.7,"scaleY":0.7,"rotation":0.05,"width":16,"height":16}},"Light50":{"star":{"scaleX":0.5,"scaleY":0.5,"rotation":0.05,"width":16,"height":16}},"Light51":{"star":{"scaleX":1.3,"scaleY":1.3,"rotation":0.05,"width":16,"height":16}},"Light52":{"star":{"scaleX":0.8,"scaleY":0.8,"rotation":0.05,"width":16,"height":16}},"Light53":{"star":{"scaleX":1.5,"scaleY":1.5,"rotation":0.05,"width":16,"height":16}}}},"animations":{"Static":{"bones":{"SCALE_720":{"translate":[{"time":0.1667,"x":0,"y":0}]}}},"animation":{"slots":{"L":{"color":[{"time":0,"color":"ffffff00","curve":"stepped"},{"time":0.0667,"color":"ffffff00","curve":[0.25,0,0.75,1]},{"time":0.2333,"color":"ffffffff","curve":[0.25,0,0.75,1]},{"time":1.0333,"color":"ffffff00"}],"attachment":[{"time":0,"name":"Light"}]},"L2":{"color":[{"time":0,"color":"ffffff00","curve":"stepped"},{"time":0.1,"color":"ffffff00","curve":[0.25,0,0.75,1]},{"time":0.3,"color":"ffffffff","curve":[0.25,0,0.75,1]},{"time":1.1,"color":"ffffff00"}],"attachment":[{"time":0,"name":"Light"}]},"L3":{"color":[{"time":0,"color":"ffffff00","curve":"stepped"},{"time":0.1667,"color":"ffffff00","curve":[0.25,0,0.75,1]},{"time":0.3333,"color":"ffffffff","curve":[0.25,0,0.75,1]},{"time":1.1333,"color":"ffffff00"}],"attachment":[{"time":0,"name":"Light"}]},"L5":{"color":[{"time":0,"color":"ffffff00","curve":[0.25,0,0.75,1]},{"time":0.1,"color":"ffffffff","curve":[0.25,0,0.75,1]},{"time":0.9,"color":"ffffff00"}],"attachment":[{"time":0,"name":"Light"}]},"L6":{"color":[{"time":0,"color":"ffffff00","curve":"stepped"},{"time":0.0667,"color":"ffffff00","curve":[0.25,0,0.75,1]},{"time":0.2333,"color":"ffffffff","curve":[0.25,0,0.75,1]},{"time":1.0333,"color":"ffffff00"}],"attachment":[{"time":0,"name":"Light"}]},"L7":{"color":[{"time":0,"color":"ffffff00","curve":"stepped"},{"time":0.0667,"color":"ffffff00","curve":[0.25,0,0.75,1]},{"time":0.2333,"color":"ffffffff","curve":[0.25,0,0.75,1]},{"time":1.0333,"color":"ffffff00"}],"attachment":[{"time":0,"name":"Light"}]},"L8":{"color":[{"time":0,"color":"ffffff00","curve":"stepped"},{"time":0.1,"color":"ffffff00","curve":[0.25,0,0.75,1]},{"time":0.3,"color":"ffffffff","curve":[0.25,0,0.75,1]},{"time":1.1,"color":"ffffff00"}],"attachment":[{"time":0,"name":"Light"}]},"L9":{"color":[{"time":0,"color":"ffffff00","curve":"stepped"},{"time":0.1667,"color":"ffffff00","curve":[0.25,0,0.75,1]},{"time":0.3333,"color":"ffffffff","curve":[0.25,0,0.75,1]},{"time":1.1333,"color":"ffffff00"}],"attachment":[{"time":0,"name":"Light"}]},"L11":{"color":[{"time":0,"color":"ffffff00","curve":[0.25,0,0.75,1]},{"time":0.1,"color":"ffffffff","curve":[0.25,0,0.75,1]},{"time":0.9,"color":"ffffff00"}],"attachment":[{"time":0,"name":"Light"}]},"L12":{"color":[{"time":0,"color":"ffffff00","curve":"stepped"},{"time":0.0667,"color":"ffffff00","curve":[0.25,0,0.75,1]},{"time":0.2333,"color":"ffffffff","curve":[0.25,0,0.75,1]},{"time":1.0333,"color":"ffffff00"}],"attachment":[{"time":0,"name":"Light"}]},"L_Frame":{"color":[{"time":0,"color":"ffffff00"},{"time":0.1667,"color":"ffffffff"},{"time":1.3333,"color":"ffffff00"}],"attachment":[{"time":0,"name":"Light_Frame"}]},"Light22":{"color":[{"time":0,"color":"ffffff00","curve":"stepped"},{"time":0.3333,"color":"ffffff00","curve":[0.168,0.29,0.69,0.82]},{"time":0.4333,"color":"ffffffff"}],"attachment":[{"time":0,"name":"star"}]},"Light23":{"color":[{"time":0,"color":"ffffff00","curve":"stepped"},{"time":0.3333,"color":"ffffff00","curve":[0.168,0.29,0.69,0.82]},{"time":0.4333,"color":"ffffffff"}],"attachment":[{"time":0,"name":"star"}]},"Light24":{"color":[{"time":0,"color":"ffffff00","curve":[0.168,0.29,0.69,0.82]},{"time":0.1,"color":"ffffffff"}],"attachment":[{"time":0,"name":"star"}]},"Light25":{"color":[{"time":0,"color":"ffffff00","curve":[0.168,0.29,0.69,0.82]},{"time":0.1,"color":"ffffffff"}],"attachment":[{"time":0,"name":"star"}]},"Light26":{"color":[{"time":0,"color":"ffffff00","curve":"stepped"},{"time":0.2333,"color":"ffffff00","curve":[0.168,0.29,0.69,0.82]},{"time":0.3333,"color":"ffffffff"}],"attachment":[{"time":0,"name":"star"}]},"Light27":{"color":[{"time":0,"color":"ffffff00","curve":"stepped"},{"time":0.1667,"color":"ffffff00","curve":[0.168,0.29,0.69,0.82]},{"time":0.2667,"color":"ffffffff"}],"attachment":[{"time":0,"name":"star"}]},"Light28":{"color":[{"time":0,"color":"ffffff00","curve":[0.168,0.29,0.69,0.82]},{"time":0.1,"color":"ffffffff"}],"attachment":[{"time":0,"name":"star"}]},"Light29":{"color":[{"time":0,"color":"ffffff00","curve":"stepped"},{"time":0.2333,"color":"ffffff00","curve":[0.168,0.29,0.69,0.82]},{"time":0.3333,"color":"ffffffff"}],"attachment":[{"time":0,"name":"star"}]},"Light30":{"color":[{"time":0,"color":"ffffff00","curve":[0.168,0.29,0.69,0.82]},{"time":0.1,"color":"ffffffff"}],"attachment":[{"time":0,"name":"star"}]},"Light31":{"color":[{"time":0,"color":"ffffff00","curve":[0.168,0.29,0.69,0.82]},{"time":0.1,"color":"ffffffff"}],"attachment":[{"time":0,"name":"star"}]},"Light32":{"color":[{"time":0,"color":"ffffff00","curve":"stepped"},{"time":0.1667,"color":"ffffff00","curve":[0.168,0.29,0.69,0.82]},{"time":0.2667,"color":"ffffffff"}],"attachment":[{"time":0,"name":"star"}]},"Light33":{"color":[{"time":0,"color":"ffffff00","curve":"stepped"},{"time":0.2333,"color":"ffffff00","curve":[0.168,0.29,0.69,0.82]},{"time":0.3333,"color":"ffffffff"}],"attachment":[{"time":0,"name":"star"}]},"Light34":{"color":[{"time":0,"color":"ffffff00","curve":"stepped"},{"time":0.1333,"color":"ffffff00","curve":[0.168,0.29,0.69,0.82]},{"time":0.2333,"color":"ffffffff"}],"attachment":[{"time":0,"name":"star"}]},"Light35":{"color":[{"time":0,"color":"ffffff00","curve":"stepped"},{"time":0.2667,"color":"ffffff00","curve":[0.168,0.29,0.69,0.82]},{"time":0.3667,"color":"ffffffff"}],"attachment":[{"time":0,"name":"star"}]},"Light36":{"color":[{"time":0,"color":"ffffff00","curve":[0.168,0.29,0.69,0.82]},{"time":0.1,"color":"ffffffff"}],"attachment":[{"time":0,"name":"star"}]},"Light37":{"color":[{"time":0,"color":"ffffff00","curve":[0.168,0.29,0.69,0.82]},{"time":0.1,"color":"ffffffff"}],"attachment":[{"time":0,"name":"star"}]},"Light38":{"color":[{"time":0,"color":"ffffff00","curve":"stepped"},{"time":0.2667,"color":"ffffff00","curve":[0.168,0.29,0.69,0.82]},{"time":0.3667,"color":"ffffffff"}],"attachment":[{"time":0,"name":"star"}]},"Light39":{"color":[{"time":0,"color":"ffffff00","curve":"stepped"},{"time":0.2333,"color":"ffffff00","curve":[0.168,0.29,0.69,0.82]},{"time":0.3333,"color":"ffffffff"}],"attachment":[{"time":0,"name":"star"}]},"Light40":{"color":[{"time":0,"color":"ffffff00","curve":"stepped"},{"time":0.3667,"color":"ffffff00","curve":[0.168,0.29,0.69,0.82]},{"time":0.4667,"color":"ffffffff"}],"attachment":[{"time":0,"name":"star"}]},"Light41":{"color":[{"time":0,"color":"ffffff00","curve":"stepped"},{"time":0.2667,"color":"ffffff00","curve":[0.168,0.29,0.69,0.82]},{"time":0.3667,"color":"ffffffff"}],"attachment":[{"time":0,"name":"star"}]},"Light42":{"color":[{"time":0,"color":"ffffff00","curve":[0.168,0.29,0.69,0.82]},{"time":0.1,"color":"ffffffff"}],"attachment":[{"time":0,"name":"star"}]},"Light43":{"color":[{"time":0,"color":"ffffff00","curve":[0.168,0.29,0.69,0.82]},{"time":0.1,"color":"ffffffff"}],"attachment":[{"time":0,"name":"star"}]},"Light44":{"color":[{"time":0,"color":"ffffff00","curve":[0.168,0.29,0.69,0.82]},{"time":0.1,"color":"ffffffff"}],"attachment":[{"time":0,"name":"star"}]},"Light45":{"color":[{"time":0,"color":"ffffff00","curve":"stepped"},{"time":0.2333,"color":"ffffff00","curve":[0.168,0.29,0.69,0.82]},{"time":0.3333,"color":"ffffffff"}],"attachment":[{"time":0,"name":"star"}]},"Light46":{"color":[{"time":0,"color":"ffffff00","curve":"stepped"},{"time":0.1333,"color":"ffffff00","curve":[0.168,0.29,0.69,0.82]},{"time":0.2333,"color":"ffffffff"}],"attachment":[{"time":0,"name":"star"}]},"Light47":{"color":[{"time":0,"color":"ffffff00","curve":"stepped"},{"time":0.2667,"color":"ffffff00","curve":[0.168,0.29,0.69,0.82]},{"time":0.3667,"color":"ffffffff"}],"attachment":[{"time":0,"name":"star"}]},"Light48":{"color":[{"time":0,"color":"ffffff00","curve":[0.168,0.29,0.69,0.82]},{"time":0.1,"color":"ffffffff"}],"attachment":[{"time":0,"name":"star"}]},"Light49":{"color":[{"time":0,"color":"ffffff00","curve":"stepped"},{"time":0.2667,"color":"ffffff00","curve":[0.168,0.29,0.69,0.82]},{"time":0.3667,"color":"ffffffff"}],"attachment":[{"time":0,"name":"star"}]},"Light50":{"color":[{"time":0,"color":"ffffff00","curve":"stepped"},{"time":0.2333,"color":"ffffff00","curve":[0.168,0.29,0.69,0.82]},{"time":0.3333,"color":"ffffffff"}],"attachment":[{"time":0,"name":"star"}]},"Light51":{"color":[{"time":0,"color":"ffffff00","curve":"stepped"},{"time":0.3667,"color":"ffffff00","curve":[0.168,0.29,0.69,0.82]},{"time":0.4667,"color":"ffffffff"}],"attachment":[{"time":0,"name":"star"}]},"Light52":{"color":[{"time":0,"color":"ffffff00","curve":"stepped"},{"time":0.2667,"color":"ffffff00","curve":[0.168,0.29,0.69,0.82]},{"time":0.3667,"color":"ffffffff"}],"attachment":[{"time":0,"name":"star"}]},"Light53":{"color":[{"time":0,"color":"ffffff00","curve":[0.168,0.29,0.69,0.82]},{"time":0.1,"color":"ffffffff"}],"attachment":[{"time":0,"name":"star"}]}},"bones":{"Light31":{"translate":[{"time":0,"x":189.63,"y":57.92,"curve":[0.168,0.29,0.69,0.82]},{"time":0.5,"x":212.2,"y":72.28}],"scale":[{"time":0,"x":1.4,"y":1.4,"curve":[0.168,0.29,0.69,0.82]},{"time":0.5,"x":0,"y":0}]},"Light22":{"translate":[{"time":0,"x":199.33,"y":52.34,"curve":"stepped"},{"time":0.3333,"x":199.33,"y":52.34,"curve":[0.168,0.29,0.69,0.82]},{"time":0.8333,"x":231.43,"y":67.77}],"scale":[{"time":0,"x":1.4,"y":1.4,"curve":"stepped"},{"time":0.3333,"x":1.4,"y":1.4,"curve":[0.168,0.29,0.69,0.82]},{"time":0.8333,"x":0,"y":0}]},"Light38":{"translate":[{"time":0,"x":208.3,"y":-22.81,"curve":"stepped"},{"time":0.2667,"x":208.3,"y":-22.81,"curve":[0.167,0.28,0.665,0.78]},{"time":0.7667,"x":246.43,"y":-35.13}],"scale":[{"time":0,"x":1.229,"y":1.229,"curve":"stepped"},{"time":0.2667,"x":1.229,"y":1.229,"curve":[0.168,0.29,0.69,0.82]},{"time":0.7667,"x":0,"y":0}]},"Light24":{"translate":[{"time":0,"x":209.5,"y":10.1,"curve":[0.168,0.29,0.69,0.82]},{"time":0.5,"x":256.31,"y":11.02}],"scale":[{"time":0,"x":1.4,"y":1.4,"curve":[0.168,0.29,0.69,0.82]},{"time":0.5,"x":0,"y":0}]},"Light30":{"translate":[{"time":0,"x":209.89,"y":26.84,"curve":[0.168,0.29,0.69,0.82]},{"time":0.5,"x":249.26,"y":52.19}],"scale":[{"time":0,"x":1.4,"y":1.4,"curve":[0.168,0.29,0.69,0.82]},{"time":0.5,"x":0,"y":0}]},"Light42":{"translate":[{"time":0,"x":210.75,"y":-48.32,"curve":[0.167,0.28,0.665,0.78]},{"time":0.5,"x":246.36,"y":-67.41}],"scale":[{"time":0,"x":1.4,"y":1.4,"curve":[0.168,0.29,0.69,0.82]},{"time":0.5,"x":0,"y":0}]},"Light27":{"translate":[{"time":0,"x":208.51,"y":-8.55,"curve":"stepped"},{"time":0.1667,"x":208.51,"y":-8.55,"curve":[0.168,0.29,0.69,0.82]},{"time":0.6667,"x":247.61,"y":-15.32}],"scale":[{"time":0,"x":1.4,"y":1.4,"curve":"stepped"},{"time":0.1667,"x":1.4,"y":1.4,"curve":[0.168,0.29,0.69,0.82]},{"time":0.6667,"x":0,"y":0}]},"Light40":{"translate":[{"time":0,"x":211.71,"y":-18.65,"curve":"stepped"},{"time":0.3667,"x":211.71,"y":-18.65,"curve":[0.167,0.28,0.665,0.78]},{"time":0.8667,"x":267.3,"y":-30.62}],"scale":[{"time":0,"x":1.249,"y":1.249,"curve":"stepped"},{"time":0.3667,"x":1.249,"y":1.249,"curve":[0.168,0.29,0.69,0.82]},{"time":0.8667,"x":0,"y":0}]},"Light33":{"translate":[{"time":0,"x":210,"y":19.67,"curve":"stepped"},{"time":0.2333,"x":210,"y":19.67,"curve":[0.167,0.28,0.665,0.78]},{"time":0.7333,"x":267.42,"y":31.82}],"scale":[{"time":0,"x":1.614,"y":1.614,"curve":"stepped"},{"time":0.2333,"x":1.614,"y":1.614,"curve":[0.168,0.29,0.69,0.82]},{"time":0.7333,"x":0,"y":0}]},"Light35":{"translate":[{"time":0,"x":202.75,"y":-30.88,"curve":"stepped"},{"time":0.2667,"x":202.75,"y":-30.88,"curve":[0.167,0.28,0.665,0.78]},{"time":0.7667,"x":257.33,"y":-55.74}],"scale":[{"time":0,"x":1.4,"y":1.4,"curve":"stepped"},{"time":0.2667,"x":1.4,"y":1.4,"curve":[0.168,0.29,0.69,0.82]},{"time":0.7667,"x":0,"y":0}]},"Light39":{"translate":[{"time":0,"x":210.49,"y":-35.22,"curve":"stepped"},{"time":0.2333,"x":210.49,"y":-35.22,"curve":[0.167,0.28,0.665,0.78]},{"time":0.7333,"x":279.92,"y":-40.87}],"scale":[{"time":0,"x":1.4,"y":1.4,"curve":"stepped"},{"time":0.2333,"x":1.4,"y":1.4,"curve":[0.168,0.29,0.69,0.82]},{"time":0.7333,"x":0,"y":0}]},"Light36":{"translate":[{"time":0,"x":208.61,"y":-4.43,"curve":[0.167,0.28,0.665,0.78]},{"time":0.5,"x":270.45,"y":-5.43}],"scale":[{"time":0,"x":1.4,"y":1.4,"curve":[0.168,0.29,0.69,0.82]},{"time":0.5,"x":0,"y":0}]},"Light41":{"translate":[{"time":0,"x":205.93,"y":-38.93,"curve":"stepped"},{"time":0.2667,"x":205.93,"y":-38.93,"curve":[0.167,0.28,0.665,0.78]},{"time":0.7667,"x":247.24,"y":-88.38}],"scale":[{"time":0,"x":1.4,"y":1.4,"curve":"stepped"},{"time":0.2667,"x":1.4,"y":1.4,"curve":[0.168,0.29,0.69,0.82]},{"time":0.7667,"x":0,"y":0}]},"Light28":{"translate":[{"time":0,"x":208.69,"y":-13.33,"curve":[0.168,0.29,0.69,0.82]},{"time":0.5,"x":267.2,"y":-31.53}],"scale":[{"time":0,"x":1.4,"y":1.4,"curve":[0.168,0.29,0.69,0.82]},{"time":0.5,"x":0,"y":0}]},"Light34":{"translate":[{"time":0,"x":192.95,"y":-49.44,"curve":"stepped"},{"time":0.1333,"x":192.95,"y":-49.44,"curve":[0.167,0.28,0.665,0.78]},{"time":0.6333,"x":240.3,"y":-92.14}],"scale":[{"time":0,"x":1.4,"y":1.4,"curve":"stepped"},{"time":0.1333,"x":1.4,"y":1.4,"curve":[0.168,0.29,0.69,0.82]},{"time":0.6333,"x":0,"y":0}]},"Light26":{"translate":[{"time":0,"x":209.6,"y":44.26,"curve":"stepped"},{"time":0.2333,"x":209.6,"y":44.26,"curve":[0.168,0.29,0.69,0.82]},{"time":0.7333,"x":241.44,"y":66.77}],"scale":[{"time":0,"x":1.4,"y":1.4,"curve":"stepped"},{"time":0.2333,"x":1.4,"y":1.4,"curve":[0.168,0.29,0.69,0.82]},{"time":0.7333,"x":0,"y":0}]},"Light23":{"translate":[{"time":0,"x":199.33,"y":52.34,"curve":"stepped"},{"time":0.3333,"x":199.33,"y":52.34,"curve":[0.168,0.29,0.69,0.82]},{"time":0.8333,"x":231.43,"y":67.77}],"scale":[{"time":0,"x":1.4,"y":1.4,"curve":"stepped"},{"time":0.3333,"x":1.4,"y":1.4,"curve":[0.168,0.29,0.69,0.82]},{"time":0.8333,"x":0,"y":0}]},"Light25":{"translate":[{"time":0,"x":209.5,"y":10.1,"curve":[0.168,0.29,0.69,0.82]},{"time":0.5,"x":256.31,"y":11.02}],"scale":[{"time":0,"x":1.4,"y":1.4,"curve":[0.168,0.29,0.69,0.82]},{"time":0.5,"x":0,"y":0}]},"Light29":{"translate":[{"time":0,"x":209.6,"y":44.26,"curve":"stepped"},{"time":0.2333,"x":209.6,"y":44.26,"curve":[0.168,0.29,0.69,0.82]},{"time":0.7333,"x":241.44,"y":66.77}],"scale":[{"time":0,"x":1.4,"y":1.4,"curve":"stepped"},{"time":0.2333,"x":1.4,"y":1.4,"curve":[0.168,0.29,0.69,0.82]},{"time":0.7333,"x":0,"y":0}]},"Light32":{"translate":[{"time":0,"x":208.51,"y":-8.55,"curve":"stepped"},{"time":0.1667,"x":208.51,"y":-8.55,"curve":[0.168,0.29,0.69,0.82]},{"time":0.6667,"x":247.61,"y":-15.32}],"scale":[{"time":0,"x":1.4,"y":1.4,"curve":"stepped"},{"time":0.1667,"x":1.4,"y":1.4,"curve":[0.168,0.29,0.69,0.82]},{"time":0.6667,"x":0,"y":0}]},"Light37":{"translate":[{"time":0,"x":208.69,"y":-13.33,"curve":[0.168,0.29,0.69,0.82]},{"time":0.5,"x":267.2,"y":-31.53}],"scale":[{"time":0,"x":1.4,"y":1.4,"curve":[0.168,0.29,0.69,0.82]},{"time":0.5,"x":0,"y":0}]},"Light43":{"translate":[{"time":0,"x":209.89,"y":26.84,"curve":[0.168,0.29,0.69,0.82]},{"time":0.5,"x":249.26,"y":52.19}],"scale":[{"time":0,"x":1.4,"y":1.4,"curve":[0.168,0.29,0.69,0.82]},{"time":0.5,"x":0,"y":0}]},"Light44":{"translate":[{"time":0,"x":189.63,"y":57.92,"curve":[0.168,0.29,0.69,0.82]},{"time":0.5,"x":212.2,"y":72.28}],"scale":[{"time":0,"x":1.4,"y":1.4,"curve":[0.168,0.29,0.69,0.82]},{"time":0.5,"x":0,"y":0}]},"Light45":{"translate":[{"time":0,"x":210,"y":19.67,"curve":"stepped"},{"time":0.2333,"x":210,"y":19.67,"curve":[0.167,0.28,0.665,0.78]},{"time":0.7333,"x":267.42,"y":31.82}],"scale":[{"time":0,"x":1.614,"y":1.614,"curve":"stepped"},{"time":0.2333,"x":1.614,"y":1.614,"curve":[0.168,0.29,0.69,0.82]},{"time":0.7333,"x":0,"y":0}]},"Light46":{"translate":[{"time":0,"x":192.95,"y":-49.44,"curve":"stepped"},{"time":0.1333,"x":192.95,"y":-49.44,"curve":[0.167,0.28,0.665,0.78]},{"time":0.6333,"x":240.3,"y":-92.14}],"scale":[{"time":0,"x":1.4,"y":1.4,"curve":"stepped"},{"time":0.1333,"x":1.4,"y":1.4,"curve":[0.168,0.29,0.69,0.82]},{"time":0.6333,"x":0,"y":0}]},"Light47":{"translate":[{"time":0,"x":202.75,"y":-30.88,"curve":"stepped"},{"time":0.2667,"x":202.75,"y":-30.88,"curve":[0.167,0.28,0.665,0.78]},{"time":0.7667,"x":257.33,"y":-55.74}],"scale":[{"time":0,"x":1.4,"y":1.4,"curve":"stepped"},{"time":0.2667,"x":1.4,"y":1.4,"curve":[0.168,0.29,0.69,0.82]},{"time":0.7667,"x":0,"y":0}]},"Light48":{"translate":[{"time":0,"x":208.61,"y":-4.43,"curve":[0.167,0.28,0.665,0.78]},{"time":0.5,"x":270.45,"y":-5.43}],"scale":[{"time":0,"x":1.4,"y":1.4,"curve":[0.168,0.29,0.69,0.82]},{"time":0.5,"x":0,"y":0}]},"Light49":{"translate":[{"time":0,"x":208.3,"y":-22.81,"curve":"stepped"},{"time":0.2667,"x":208.3,"y":-22.81,"curve":[0.167,0.28,0.665,0.78]},{"time":0.7667,"x":246.43,"y":-35.13}],"scale":[{"time":0,"x":1.229,"y":1.229,"curve":"stepped"},{"time":0.2667,"x":1.229,"y":1.229,"curve":[0.168,0.29,0.69,0.82]},{"time":0.7667,"x":0,"y":0}]},"Light50":{"translate":[{"time":0,"x":210.49,"y":-35.22,"curve":"stepped"},{"time":0.2333,"x":210.49,"y":-35.22,"curve":[0.167,0.28,0.665,0.78]},{"time":0.7333,"x":279.92,"y":-40.87}],"scale":[{"time":0,"x":1.4,"y":1.4,"curve":"stepped"},{"time":0.2333,"x":1.4,"y":1.4,"curve":[0.168,0.29,0.69,0.82]},{"time":0.7333,"x":0,"y":0}]},"Light51":{"translate":[{"time":0,"x":211.71,"y":-18.65,"curve":"stepped"},{"time":0.3667,"x":211.71,"y":-18.65,"curve":[0.167,0.28,0.665,0.78]},{"time":0.8667,"x":267.3,"y":-30.62}],"scale":[{"time":0,"x":1.249,"y":1.249,"curve":"stepped"},{"time":0.3667,"x":1.249,"y":1.249,"curve":[0.168,0.29,0.69,0.82]},{"time":0.8667,"x":0,"y":0}]},"Light52":{"translate":[{"time":0,"x":205.93,"y":-38.93,"curve":"stepped"},{"time":0.2667,"x":205.93,"y":-38.93,"curve":[0.167,0.28,0.665,0.78]},{"time":0.7667,"x":247.24,"y":-88.38}],"scale":[{"time":0,"x":1.4,"y":1.4,"curve":"stepped"},{"time":0.2667,"x":1.4,"y":1.4,"curve":[0.168,0.29,0.69,0.82]},{"time":0.7667,"x":0,"y":0}]},"Light53":{"translate":[{"time":0,"x":210.75,"y":-48.32,"curve":[0.167,0.28,0.665,0.78]},{"time":0.5,"x":246.36,"y":-67.41}],"scale":[{"time":0,"x":1.4,"y":1.4,"curve":[0.168,0.29,0.69,0.82]},{"time":0.5,"x":0,"y":0}]},"All_Light_Particle2":{"scale":[{"time":0,"x":1,"y":-1}]},"All_Light_Particle3":{"scale":[{"time":0,"x":1,"y":-1}]}}}}},[0]]],0,0,[0],[-1],[0]]